{"ysize":100,"name":"Habitat","description":"Habitat","xsize":100,"animals":[{"positiony":50,"species":"Wolf","name":"wolf1","description":"wolf","sightings":[{"positiony":50,"date":"2000-01-01 00:00","animal":"model.Wolf@467fba5e","description":"Initial Sighting of wolf1, wolf","positionx":50}],"positionx":50},{"positiony":0,"species":"Deer","name":"deer1","description":"deer","sightings":[{"positiony":0,"date":"2000-01-01 00:00","animal":"model.Deer@77bcfad0","description":"Initial Sighting of deer1, deer","positionx":0}],"positionx":0},{"positiony":12,"species":"Wolf","name":"wolf2","description":"test2","sightings":[{"positiony":12,"date":"2000-01-01 12:00","animal":"model.Wolf@26c8f63c","description":"Initial Sighting of wolf2, test2","positionx":12}],"positionx":12}]}